requirements.txt
setup.py
jsfiddle_factory/__init__.py
jsfiddle_factory/__main__.py
jsfiddle_factory/build.py
jsfiddle_factory/detox.py
jsfiddle_factory/init.py
jsfiddle_factory/readme.py
jsfiddle_factory.egg-info/PKG-INFO
jsfiddle_factory.egg-info/SOURCES.txt
jsfiddle_factory.egg-info/dependency_links.txt
jsfiddle_factory.egg-info/requires.txt
jsfiddle_factory.egg-info/top_level.txt