Metadata-Version: 2.1
Name: jsfiddle-factory
Version: 2020.7.1
Summary: jsfiddle mass generator
Home-page: https://github.com/andrewp-as-is/jsfiddle-factory.py
License: Unlicense
Keywords: jsfiddle
Platform: UNKNOWN
Classifier: License :: Public Domain
Classifier: Operating System :: OS Independent
Classifier: Programming Language :: Python :: 3
